pymbs/__init__.py
pymbs/__version__.py
pymbs/api.py
pymbs/config.py
pymbs/core.py
pymbs/enums.py
pymbs/exceptions.py
pymbs/log.py
pymbs/payment_rules.py
pymbs/tranche.py
pymbs/utils.py
pymbs/config/pymbs_logging.json
pymbs/templates/no_config.j2
pymbs/templates/no_config_data.j2
pymbs/templates/no_data.j2
pymbs/templates/no_file.j2
pymbs/templates/rounding_error.j2
pymbs/templates/rounding_error_wals.j2
pymbs-0.3.1.dist-info/LICENSE
pymbs-0.3.1.dist-info/METADATA
pymbs-0.3.1.dist-info/WHEEL
pymbs-0.3.1.dist-info/top_level.txt
pymbs-0.3.1.dist-info/RECORD
