Metadata-Version: 2.1
Name: pymbs
Version: 0.3.1
Summary: A library for use in modeling Mortgage-Backed Securities.
Home-page: https://pypi.org/project/pymbs/
Author: Brian Farrell
Author-email: brian.farrell@me.com
License: AGPLv3
Keywords: financial modeling analysis mortgage securities
Classifier: Development Status :: 1 - Planning
Classifier: Intended Audience :: Financial and Insurance Industry
Classifier: License :: OSI Approved :: GNU Affero General Public License v3
Classifier: License :: OSI Approved :: GNU Affero General Public License v3 or later (AGPLv3+)
Classifier: Topic :: Office/Business :: Financial
Classifier: Topic :: Office/Business :: Financial :: Investment
Classifier: Topic :: Software Development :: Libraries
Classifier: Operating System :: POSIX
Classifier: Programming Language :: Python
Classifier: Programming Language :: Python :: 3
Classifier: Programming Language :: Python :: 3.6
Classifier: Programming Language :: Python :: 3.7
Classifier: Programming Language :: Python :: Implementation :: CPython
Requires-Python: >=3.10.0
License-File: LICENSE
Requires-Dist: ipython (>=8.14.0)
Requires-Dist: jinja2 (>=3.1.2)
Requires-Dist: numpy (>=1.23.5)
Requires-Dist: numpy-financial (>=1.0.0)
Requires-Dist: pandas (>=2.0.2)
Requires-Dist: pyyaml (>=6.0)
